forgepy/__init__.py
forgepy/forgepy.py
minecraft_forgePY-1.0.3.dist-info/METADATA
minecraft_forgePY-1.0.3.dist-info/WHEEL
minecraft_forgePY-1.0.3.dist-info/top_level.txt
minecraft_forgePY-1.0.3.dist-info/RECORD
