Metadata-Version: 2.1
Name: minecraft-forgePY
Version: 1.0.3
Summary: Get Minecraft Forge download URLs.
Author: matejmajny
Keywords: python,minecraft,forge,API,forgepy
Requires-Dist: requests
Requires-Dist: bs4
